league_client_live_data/__init__.py
league_client_live_data/config.py
league_client_live_data/config.yaml
league_client_live_data/endpoint_data/__init__.py
league_client_live_data/endpoint_data/abilities.py
league_client_live_data/endpoint_data/all_game_data.py
league_client_live_data/endpoint_data/champion_stata.py
league_client_live_data/endpoint_data/event.py
league_client_live_data/endpoint_data/game_data.py
league_client_live_data/endpoint_data/player.py
league_client_live_data/endpoint_data/runes.py
league_client_live_data/endpoint_data/summoner_spell.py
league_client_live_data/live_client_data.py
league_client_live_data/utils.py
leagueclientlivedata-0.1.2.dist-info/LICENSE
leagueclientlivedata-0.1.2.dist-info/WHEEL
leagueclientlivedata-0.1.2.dist-info/METADATA
leagueclientlivedata-0.1.2.dist-info/RECORD
