Metadata-Version: 2.1
Name: leagueclientlivedata
Version: 0.1.2
Summary: 
Author: Lukas Mahr
Author-email: lukas@yousuckatprogramming.de
Requires-Python: >=3.10
Classifier: Programming Language :: Python :: 3
Classifier: Programming Language :: Python :: 3.10
Classifier: Programming Language :: Python :: 3.11
Requires-Dist: black (>=23.3.0,<24.0.0)
Requires-Dist: httpx (>=0.24.0,<0.25.0)
Requires-Dist: mypy (>=1.2.0,<2.0.0)
Requires-Dist: pydantic (>=1.10.7,<2.0.0)
Requires-Dist: pylint (>=2.17.2,<3.0.0)
Requires-Dist: pyyaml (>=6.0,<7.0)
Requires-Dist: ruff (>=0.0.262,<0.0.263)
Requires-Dist: types-pyyaml (>=6.0.12.9,<7.0.0.0)
